data_sync/__init__.py
data_sync/admin.py
data_sync/apps.py
data_sync/exceptions.py
data_sync/managers.py
data_sync/models.py
data_sync/registration.py
data_sync/runtime_utils.py
data_sync/tests.py
data_sync/url_constants.py
data_sync/urls.py
data_sync/views.py
data_sync/migrations/0001_initial.py
data_sync/migrations/0002_auto_20190528_0217.py
data_sync/migrations/0003_datapull_status.py
data_sync/migrations/0004_auto_20190602_2335.py
data_sync/migrations/0005_auto_20190603_0710.py
data_sync/migrations/__init__.py
django_data_sync-0.5.2.dist-info/LICENSE
django_data_sync-0.5.2.dist-info/METADATA
django_data_sync-0.5.2.dist-info/WHEEL
django_data_sync-0.5.2.dist-info/top_level.txt
django_data_sync-0.5.2.dist-info/RECORD
