Metadata-Version: 2.1
Name: django-data-sync
Version: 0.5.2
Summary: Sync database between Django backends
Home-page: http://github.com/unit9/django-data-sync
Author: Abirafdi Raditya Putra
Author-email: raditya.putra@unit9.com
License: MIT
Platform: UNKNOWN
Classifier: Environment :: Web Environment
Classifier: Framework :: Django
Classifier: Framework :: Django :: 2.2
Classifier: Intended Audience :: Developers
Classifier: License :: OSI Approved :: MIT License
Classifier: Operating System :: OS Independent
Classifier: Programming Language :: Python
Classifier: Programming Language :: Python :: 3.7
Classifier: Topic :: Internet :: WWW/HTTP
Classifier: Topic :: Internet :: WWW/HTTP :: Dynamic Content
Requires-Python: >=3.7
Requires-Dist: requests
Requires-Dist: google-cloud-tasks (==1.1.0)
Requires-Dist: cryptography (==2.7)
Requires-Dist: PyJWT (==1.7.1)
Requires-Dist: oidc-validators (==0.5.2)
